odoo/addons/account_invoice_force_origin/README.rst
odoo/addons/account_invoice_force_origin/__init__.py
odoo/addons/account_invoice_force_origin/__manifest__.py
odoo/addons/account_invoice_force_origin/i18n/account_invoice_force_origin.pot
odoo/addons/account_invoice_force_origin/readme/CONFIGURE.rst
odoo/addons/account_invoice_force_origin/readme/CONTRIBUTORS.rst
odoo/addons/account_invoice_force_origin/readme/DESCRIPTION.rst
odoo/addons/account_invoice_force_origin/readme/USAGE.rst
odoo/addons/account_invoice_force_origin/security/security.xml
odoo/addons/account_invoice_force_origin/static/description/icon.png
odoo/addons/account_invoice_force_origin/static/description/index.html
odoo/addons/account_invoice_force_origin/views/account_move_view.xml
odoo13_addon_account_invoice_force_origin-13.0.1.0.1.dev2.dist-info/METADATA
odoo13_addon_account_invoice_force_origin-13.0.1.0.1.dev2.dist-info/WHEEL
odoo13_addon_account_invoice_force_origin-13.0.1.0.1.dev2.dist-info/top_level.txt
odoo13_addon_account_invoice_force_origin-13.0.1.0.1.dev2.dist-info/RECORD
